w1hack/__init__.py
w1hack/courses.py
w1hack/utils.py
w1hack-0.4.0.dist-info/METADATA
w1hack-0.4.0.dist-info/WHEEL
w1hack-0.4.0.dist-info/top_level.txt
w1hack-0.4.0.dist-info/RECORD
