Metadata-Version: 2.1
Name: w1hack
Version: 0.4.0
Summary: Una biblioteca para consultar cursos de hack4u.
Home-page: https://hack4u.io
Author: Marcelo Vazquez
